odoo/addons/ssi_financial_budget/README.rst
odoo/addons/ssi_financial_budget/__init__.py
odoo/addons/ssi_financial_budget/__manifest__.py
odoo/addons/ssi_financial_budget/menu.xml
odoo/addons/ssi_financial_budget/data/approval_template_data.xml
odoo/addons/ssi_financial_budget/data/ir_sequence_data.xml
odoo/addons/ssi_financial_budget/data/policy_template_data.xml
odoo/addons/ssi_financial_budget/data/sequence_template_data.xml
odoo/addons/ssi_financial_budget/demo/financial_budget_type_demo.xml
odoo/addons/ssi_financial_budget/models/__init__.py
odoo/addons/ssi_financial_budget/models/financial_budget_account.py
odoo/addons/ssi_financial_budget/models/financial_budget_budget.py
odoo/addons/ssi_financial_budget/models/financial_budget_detail.py
odoo/addons/ssi_financial_budget/models/financial_budget_detail_summary.py
odoo/addons/ssi_financial_budget/models/financial_budget_move_line.py
odoo/addons/ssi_financial_budget/models/financial_budget_move_line_summary.py
odoo/addons/ssi_financial_budget/models/financial_budget_summary.py
odoo/addons/ssi_financial_budget/models/financial_budget_type.py
odoo/addons/ssi_financial_budget/models/res_config_settings.py
odoo/addons/ssi_financial_budget/security/ir.model.access.csv
odoo/addons/ssi_financial_budget/security/ir_module_category_data.xml
odoo/addons/ssi_financial_budget/security/ir_rule_data.xml
odoo/addons/ssi_financial_budget/security/res_group_data.xml
odoo/addons/ssi_financial_budget/static/description/banner.png
odoo/addons/ssi_financial_budget/static/description/icon.png
odoo/addons/ssi_financial_budget/views/financial_budget_budget_views.xml
odoo/addons/ssi_financial_budget/views/financial_budget_type_views.xml
odoo/addons/ssi_financial_budget/views/res_config_settings_views.xml
odoo14_addon_ssi_financial_budget-14.0.1.3.0.dist-info/METADATA
odoo14_addon_ssi_financial_budget-14.0.1.3.0.dist-info/WHEEL
odoo14_addon_ssi_financial_budget-14.0.1.3.0.dist-info/top_level.txt
odoo14_addon_ssi_financial_budget-14.0.1.3.0.dist-info/RECORD
