Metadata-Version: 2.1
Name: odoo14-addon-ssi-financial-budget
Version: 14.0.1.3.0
Summary: Financial Budget
Home-page: https://simetri-sinergi.id
Author: OpenSynergy Indonesia, PT. Simetri Sinergi Indonesia
License: AGPL-3
Platform: UNKNOWN
Classifier: Programming Language :: Python
Classifier: Framework :: Odoo
Classifier: Framework :: Odoo :: 14.0
Classifier: License :: OSI Approved :: GNU Affero General Public License v3
Requires-Python: >=3.6
Requires-Dist: odoo14-addon-account-fiscal-month
Requires-Dist: odoo14-addon-ssi-company-currency-mixin
Requires-Dist: odoo14-addon-ssi-cost-accounting
Requires-Dist: odoo14-addon-ssi-financial-accounting
Requires-Dist: odoo14-addon-ssi-master-data-mixin
Requires-Dist: odoo14-addon-ssi-product-line-price-mixin
Requires-Dist: odoo14-addon-ssi-transaction-cancel-mixin
Requires-Dist: odoo14-addon-ssi-transaction-confirm-mixin
Requires-Dist: odoo14-addon-ssi-transaction-done-mixin
Requires-Dist: odoo14-addon-ssi-transaction-open-mixin
Requires-Dist: odoo14-addon-ssi-transaction-terminate-mixin
Requires-Dist: odoo (<14.1dev,>=14.0a)
